versioneer2/__init__.py
versioneer2/_version.py
versioneer2/installer.py
versioneer2/tests/__init__.py
versioneer2/tests/test_versioneer2.py
versioneer2-0.1.10.dist-info/DESCRIPTION.rst
versioneer2-0.1.10.dist-info/entry_points.txt
versioneer2-0.1.10.dist-info/METADATA
versioneer2-0.1.10.dist-info/metadata.json
versioneer2-0.1.10.dist-info/RECORD
versioneer2-0.1.10.dist-info/top_level.txt
versioneer2-0.1.10.dist-info/WHEEL
