Metadata-Version: 2.0
Name: versioneer2
Version: 0.1.10
Summary: An updated, simplified version of versioneer"
Home-page: https://github.com/ryanpdwyer/versioneer2
Author: Ryan Dwyer
Author-email: ryanpdwyer@gmail.com
License: MIT
Keywords: versioneer2
Platform: UNKNOWN
Classifier: Development Status :: 2 - Pre-Alpha
Classifier: Intended Audience :: Developers
Classifier: License :: OSI Approved :: MIT License
Classifier: Natural Language :: English
Classifier: Programming Language :: Python :: 2
Classifier: Programming Language :: Python :: 2.7
